recline/__init__.py
recline/arg_types/__init__.py
recline/arg_types/choices.py
recline/arg_types/flag.py
recline/arg_types/positional.py
recline/arg_types/ranged_int.py
recline/arg_types/recline_type.py
recline/arg_types/recline_type_error.py
recline/arg_types/remainder.py
recline/commands/__init__.py
recline/commands/async_command.py
recline/commands/builtin_commands.py
recline/commands/cli_command.py
recline/commands/man_utils.py
recline/formatters/__init__.py
recline/formatters/output_formatter.py
recline/formatters/table_formatter.py
recline/repl/__init__.py
recline/repl/completer.py
recline/repl/shell.py
recline/vendor/__init__.py
recline/vendor/docstring_parser/LICENSE
recline/vendor/docstring_parser/__init__.py
recline/vendor/docstring_parser/parser/__init__.py
recline/vendor/docstring_parser/parser/common.py
recline/vendor/docstring_parser/parser/google.py
recline/vendor/docstring_parser/parser/rest.py
recline-2025.12.dist-info/METADATA
recline-2025.12.dist-info/WHEEL
recline-2025.12.dist-info/licenses/LICENSE
recline-2025.12.dist-info/RECORD
