Metadata-Version: 2.4
Name: recline
Version: 2025.12
Summary: Writing argparse-based command line applications can become tedious, repetitive, and difficult to do right. Relax and let this library free you from that burden.
License: BSD-3-Clause
License-File: LICENSE
Keywords: cli,interactive,shell,argparse,recline
Author: NetApp
Author-email: ng-netapp-oss@netapp.com
Requires-Python: >=3.9.0,<4
Classifier: License :: OSI Approved :: BSD License
Classifier: Programming Language :: Python :: 3
Classifier: Programming Language :: Python :: 3.9
Classifier: Programming Language :: Python :: 3.10
Classifier: Programming Language :: Python :: 3.11
Classifier: Programming Language :: Python :: 3.12
Classifier: Programming Language :: Python :: 3.13
Classifier: Programming Language :: Python :: 3.14
Classifier: Topic :: Software Development :: Libraries :: Python Modules
Classifier: Topic :: System :: Shells
Requires-Dist: argcomplete (>=3)
Requires-Dist: pyreadline3 (>=3.4.1,<4.0.0) ; sys_platform == "win32"
Requires-Dist: windows-curses (>=2.3.3,<3.0.0) ; sys_platform == "win32"
Project-URL: Documentation, https://netapp.github.io/recline
Project-URL: Homepage, https://github.com/NetApp/recline
Project-URL: Repository, https://github.com/NetApp/recline
